chess_analytica/Board.py
chess_analytica/ChessDotCom.py
chess_analytica/__init__.py
chess_analytica-1.2.4.dist-info/LICENSE.txt
chess_analytica-1.2.4.dist-info/METADATA
chess_analytica-1.2.4.dist-info/WHEEL
chess_analytica-1.2.4.dist-info/top_level.txt
chess_analytica-1.2.4.dist-info/RECORD
